topsis.py
Topsis_Dipanshu_101803691-0.0.1.dist-info/License.txt
Topsis_Dipanshu_101803691-0.0.1.dist-info/METADATA
Topsis_Dipanshu_101803691-0.0.1.dist-info/WHEEL
Topsis_Dipanshu_101803691-0.0.1.dist-info/top_level.txt
Topsis_Dipanshu_101803691-0.0.1.dist-info/RECORD
