Metadata-Version: 2.1
Name: Topsis-Dipanshu-101803691
Version: 0.0.1
Summary: it is package which tells you best value based on the data by using some mathematical calculations
Home-page: https://github.com/DipanshuGolan96/topsis
Author: Dipanshu Golan
Author-email: dipanshugolan96@gmail.com
License: UNKNOWN
Platform: UNKNOWN
Classifier: Programming Language :: Python :: 3
Classifier: License :: OSI Approved :: MIT License
Classifier: Operating System :: OS Independent
Requires-Python: >=3.6
Requires-Dist: pandas
Requires-Dist: numpy (==1.19.3)
